fragmentmnp/__init__.py
fragmentmnp/_errors.py
fragmentmnp/examples.py
fragmentmnp/fragmentmnp.py
fragmentmnp/output.py
fragmentmnp/validation.py
fragmentmnp-1.1.7.dist-info/LICENSE
fragmentmnp-1.1.7.dist-info/METADATA
fragmentmnp-1.1.7.dist-info/WHEEL
fragmentmnp-1.1.7.dist-info/RECORD
