Metadata-Version: 2.3
Name: fragmentmnp
Version: 1.1.7
Summary: Model of microplastic degradation and fragmentation in the environment
License: BSD-3-Clause
Author: Sam Harrison
Author-email: samharrison.xg@gmail.com
Requires-Python: >=3.9,<3.13
Classifier: License :: OSI Approved :: BSD License
Classifier: Programming Language :: Python :: 3
Classifier: Programming Language :: Python :: 3.9
Classifier: Programming Language :: Python :: 3.10
Classifier: Programming Language :: Python :: 3.11
Classifier: Programming Language :: Python :: 3.12
Requires-Dist: Pillow (>=9.1.1)
Requires-Dist: matplotlib (>=3.5.1,<4.0.0)
Requires-Dist: numpy (>=1.22.3,<2.0.0)
Requires-Dist: pandas (>=1.4.2,<2.0.0)
Requires-Dist: plotly (>=5.8.0,<6.0.0)
Requires-Dist: schema (>=0.7.5,<0.8.0)
Requires-Dist: scipy (>=1.8.0,<2.0.0)
Project-URL: Repository, https://github.com/microplastics-cluster/fragment-mnp
